<?xml version="1.0" encoding="UTF-8"?>
<con:soapui-project id="24389a77-c8ee-43e7-9f02-383a1e1f9a56" activeEnvironment="Default" name="TestDB" soapui-version="5.5.0" abortOnError="false" runType="SEQUENTIAL" xmlns:con="http://eviware.com/soapui/config"><con:settings/><con:interface xsi:type="con:WsdlInterface" id="092fe14d-bfa3-4bb5-b413-ed6042bd9f3c" wsaVersion="NONE" name="PersonWebServiceImplPortBinding" type="wsdl" bindingName="{http://personwsapplication.mycompany.com/}PersonWebServiceImplPortBinding" soapVersion="1_1" anonymous="optional" definition="http://localhost:8080/PersonWSApplication/PersonWebServiceImplService?WSDL" xmlns:xsi="http://www.w3.org/2001/XMLSchema-instance"><con:settings/><con:definitionCache type="TEXT" rootPart="http://localhost:8080/PersonWSApplication/PersonWebServiceImplService?WSDL"><con:part><con:url>http://localhost:8080/PersonWSApplication/PersonWebServiceImplService?WSDL</con:url><con:content><![CDATA[<!--Published by JAX-WS RI (http://jax-ws.java.net). RI's version is Metro/2.3.2-b608 (trunk-7979; 2015-01-21T12:50:19+0000) JAXWS-RI/2.2.11-b150120.1832 JAXWS-API/2.2.12 JAXB-RI/2.2.12-b141219.1637 JAXB-API/2.2.13-b141020.1521 svn-revision#unknown.-->
<!--Generated by JAX-WS RI (http://jax-ws.java.net). RI's version is Metro/2.3.2-b608 (trunk-7979; 2015-01-21T12:50:19+0000) JAXWS-RI/2.2.11-b150120.1832 JAXWS-API/2.2.12 JAXB-RI/2.2.12-b141219.1637 JAXB-API/2.2.13-b141020.1521 svn-revision#unknown.-->
<definitions targetNamespace="http://personwsapplication.mycompany.com/" name="PersonWebServiceImplService" xmlns:wsu="http://docs.oasis-open.org/wss/2004/01/oasis-200401-wss-wssecurity-utility-1.0.xsd" xmlns:wsp="http://www.w3.org/ns/ws-policy" xmlns:wsp1_2="http://schemas.xmlsoap.org/ws/2004/09/policy" xmlns:wsam="http://www.w3.org/2007/05/addressing/metadata" xmlns:soap="http://schemas.xmlsoap.org/wsdl/soap/" xmlns:tns="http://personwsapplication.mycompany.com/" xmlns:xsd="http://www.w3.org/2001/XMLSchema" xmlns="http://schemas.xmlsoap.org/wsdl/">
  <types>
    <xsd:schema>
      <xsd:import namespace="http://personwsapplication.mycompany.com/" schemaLocation="http://localhost:8080/PersonWSApplication/PersonWebServiceImplService?xsd=1"/>
    </xsd:schema>
  </types>
  <message name="RAge">
    <part name="parameters" element="tns:RAge"/>
  </message>
  <message name="RAgeResponse">
    <part name="parameters" element="tns:RAgeResponse"/>
  </message>
  <message name="RSalary">
    <part name="parameters" element="tns:RSalary"/>
  </message>
  <message name="RSalaryResponse">
    <part name="parameters" element="tns:RSalaryResponse"/>
  </message>
  <message name="RPerson">
    <part name="parameters" element="tns:RPerson"/>
  </message>
  <message name="RPersonResponse">
    <part name="parameters" element="tns:RPersonResponse"/>
  </message>
  <portType name="PersonWebServiceImpl">
    <operation name="RAge">
      <input wsam:Action="http://personwsapplication.mycompany.com/PersonWebServiceImpl/RAgeRequest" message="tns:RAge"/>
      <output wsam:Action="http://personwsapplication.mycompany.com/PersonWebServiceImpl/RAgeResponse" message="tns:RAgeResponse"/>
    </operation>
    <operation name="RSalary">
      <input wsam:Action="http://personwsapplication.mycompany.com/PersonWebServiceImpl/RSalaryRequest" message="tns:RSalary"/>
      <output wsam:Action="http://personwsapplication.mycompany.com/PersonWebServiceImpl/RSalaryResponse" message="tns:RSalaryResponse"/>
    </operation>
    <operation name="RPerson">
      <input wsam:Action="http://personwsapplication.mycompany.com/PersonWebServiceImpl/RPersonRequest" message="tns:RPerson"/>
      <output wsam:Action="http://personwsapplication.mycompany.com/PersonWebServiceImpl/RPersonResponse" message="tns:RPersonResponse"/>
    </operation>
  </portType>
  <binding name="PersonWebServiceImplPortBinding" type="tns:PersonWebServiceImpl">
    <soap:binding transport="http://schemas.xmlsoap.org/soap/http" style="document"/>
    <operation name="RAge">
      <soap:operation soapAction=""/>
      <input>
        <soap:body use="literal"/>
      </input>
      <output>
        <soap:body use="literal"/>
      </output>
    </operation>
    <operation name="RSalary">
      <soap:operation soapAction=""/>
      <input>
        <soap:body use="literal"/>
      </input>
      <output>
        <soap:body use="literal"/>
      </output>
    </operation>
    <operation name="RPerson">
      <soap:operation soapAction=""/>
      <input>
        <soap:body use="literal"/>
      </input>
      <output>
        <soap:body use="literal"/>
      </output>
    </operation>
  </binding>
  <service name="PersonWebServiceImplService">
    <port name="PersonWebServiceImplPort" binding="tns:PersonWebServiceImplPortBinding">
      <soap:address location="http://localhost:8080/PersonWSApplication/PersonWebServiceImplService"/>
    </port>
  </service>
</definitions>]]></con:content><con:type>http://schemas.xmlsoap.org/wsdl/</con:type></con:part><con:part><con:url>http://localhost:8080/PersonWSApplication/PersonWebServiceImplService?xsd=1</con:url><con:content><![CDATA[<!--Published by JAX-WS RI (http://jax-ws.java.net). RI's version is Metro/2.3.2-b608 (trunk-7979; 2015-01-21T12:50:19+0000) JAXWS-RI/2.2.11-b150120.1832 JAXWS-API/2.2.12 JAXB-RI/2.2.12-b141219.1637 JAXB-API/2.2.13-b141020.1521 svn-revision#unknown.-->
<xs:schema version="1.0" targetNamespace="http://personwsapplication.mycompany.com/" xmlns:tns="http://personwsapplication.mycompany.com/" xmlns:xs="http://www.w3.org/2001/XMLSchema">
  <xs:element name="RAge" type="tns:RAge"/>
  <xs:element name="RAgeResponse" type="tns:RAgeResponse"/>
  <xs:element name="RPerson" type="tns:RPerson"/>
  <xs:element name="RPersonResponse" type="tns:RPersonResponse"/>
  <xs:element name="RSalary" type="tns:RSalary"/>
  <xs:element name="RSalaryResponse" type="tns:RSalaryResponse"/>
  <xs:complexType name="RPerson">
    <xs:sequence/>
  </xs:complexType>
  <xs:complexType name="RPersonResponse">
    <xs:sequence>
      <xs:element name="return" type="tns:personInfo" minOccurs="0" maxOccurs="unbounded"/>
    </xs:sequence>
  </xs:complexType>
  <xs:complexType name="personInfo">
    <xs:sequence>
      <xs:element name="age" type="xs:string" minOccurs="0"/>
      <xs:element name="name" type="xs:string" minOccurs="0"/>
      <xs:element name="position" type="xs:string" minOccurs="0"/>
      <xs:element name="salary" type="xs:string" minOccurs="0"/>
    </xs:sequence>
  </xs:complexType>
  <xs:complexType name="RAge">
    <xs:sequence>
      <xs:element name="Name" type="xs:string" minOccurs="0"/>
      <xs:element name="Position" type="xs:string" minOccurs="0"/>
    </xs:sequence>
  </xs:complexType>
  <xs:complexType name="RAgeResponse">
    <xs:sequence>
      <xs:element name="return" type="xs:string" minOccurs="0"/>
    </xs:sequence>
  </xs:complexType>
  <xs:complexType name="RSalary">
    <xs:sequence>
      <xs:element name="Name" type="xs:string" minOccurs="0"/>
      <xs:element name="Position" type="xs:string" minOccurs="0"/>
    </xs:sequence>
  </xs:complexType>
  <xs:complexType name="RSalaryResponse">
    <xs:sequence>
      <xs:element name="return" type="tns:personInfo" minOccurs="0"/>
    </xs:sequence>
  </xs:complexType>
</xs:schema>]]></con:content><con:type>http://www.w3.org/2001/XMLSchema</con:type></con:part></con:definitionCache><con:endpoints><con:endpoint>http://localhost:8080/PersonWSApplication/PersonWebServiceImplService</con:endpoint></con:endpoints><con:operation id="4966be2c-9e92-40d0-b4f6-a65d01b01ece" isOneWay="false" action="" name="RAge" bindingOperationName="RAge" type="Request-Response" inputName="" receivesAttachments="false" sendsAttachments="false" anonymous="optional"><con:settings/><con:call id="7dce28bd-e099-4147-9e82-8db1f603a364" name="Request 1"><con:settings><con:setting id="com.eviware.soapui.impl.wsdl.WsdlRequest@request-headers">&lt;xml-fragment/></con:setting></con:settings><con:encoding>UTF-8</con:encoding><con:endpoint>http://localhost:8080/PersonWSApplication/PersonWebServiceImplService</con:endpoint><con:request><![CDATA[<soapenv:Envelope xmlns:soapenv="http://schemas.xmlsoap.org/soap/envelope/" xmlns:per="http://personwsapplication.mycompany.com/">\r
   <soapenv:Header/>\r
   <soapenv:Body>\r
      <per:RAge>\r
         <!--Optional:-->\r
         <Name>негнег</Name>\r
         <!--Optional:-->\r
         <Position>Главный специалист</Position>\r
      </per:RAge>\r
   </soapenv:Body>\r
</soapenv:Envelope>]]></con:request><con:credentials><con:authType>No Authorization</con:authType></con:credentials><con:jmsConfig JMSDeliveryMode="PERSISTENT"/><con:jmsPropertyConfig/><con:wsaConfig mustUnderstand="NONE" version="200508" action="http://personwsapplication.mycompany.com/PersonWebServiceImpl/RAgeRequest"/><con:wsrmConfig version="1.2"/></con:call></con:operation><con:operation id="566c9807-e159-46cb-bdf6-32a02c20f8d9" isOneWay="false" action="" name="RPerson" bindingOperationName="RPerson" type="Request-Response" inputName="" receivesAttachments="false" sendsAttachments="false" anonymous="optional"><con:settings/><con:call id="bf322417-de73-4d66-ab47-d4c3aa9f5b25" name="Request 1"><con:settings><con:setting id="com.eviware.soapui.impl.wsdl.WsdlRequest@request-headers">&lt;xml-fragment/></con:setting></con:settings><con:encoding>UTF-8</con:encoding><con:endpoint>http://localhost:8080/PersonWSApplication/PersonWebServiceImplService</con:endpoint><con:request><![CDATA[<soapenv:Envelope xmlns:soapenv="http://schemas.xmlsoap.org/soap/envelope/" xmlns:per="http://personwsapplication.mycompany.com/">\r
   <soapenv:Header/>\r
   <soapenv:Body>\r
      <per:RPerson/>\r
   </soapenv:Body>\r
</soapenv:Envelope>]]></con:request><con:credentials><con:authType>No Authorization</con:authType></con:credentials><con:jmsConfig JMSDeliveryMode="PERSISTENT"/><con:jmsPropertyConfig/><con:wsaConfig mustUnderstand="NONE" version="200508" action="http://personwsapplication.mycompany.com/PersonWebServiceImpl/RPersonRequest"/><con:wsrmConfig version="1.2"/></con:call></con:operation><con:operation id="32ae0b54-ac88-47cf-b802-05d87de6366b" isOneWay="false" action="" name="RSalary" bindingOperationName="RSalary" type="Request-Response" inputName="" receivesAttachments="false" sendsAttachments="false" anonymous="optional"><con:settings/><con:call id="84428a12-de49-4fe7-8e21-69b3845957d9" name="Request 1"><con:settings><con:setting id="com.eviware.soapui.impl.wsdl.WsdlRequest@request-headers">&lt;xml-fragment/></con:setting></con:settings><con:encoding>UTF-8</con:encoding><con:endpoint>http://localhost:8080/PersonWSApplication/PersonWebServiceImplService</con:endpoint><con:request><![CDATA[<soapenv:Envelope xmlns:soapenv="http://schemas.xmlsoap.org/soap/envelope/" xmlns:per="http://personwsapplication.mycompany.com/">\r
   <soapenv:Header/>\r
   <soapenv:Body>\r
      <per:RSalary>\r
         <!--Optional:-->\r
         <Name>Владимир Смирнов</Name>\r
         <!--Optional:-->\r
         <Position>Главный специалист</Position>\r
      </per:RSalary>\r
   </soapenv:Body>\r
</soapenv:Envelope>]]></con:request><con:credentials><con:authType>No Authorization</con:authType></con:credentials><con:jmsConfig JMSDeliveryMode="PERSISTENT"/><con:jmsPropertyConfig/><con:wsaConfig mustUnderstand="NONE" version="200508" action="http://personwsapplication.mycompany.com/PersonWebServiceImpl/RSalaryRequest"/><con:wsrmConfig version="1.2"/></con:call></con:operation></con:interface><con:properties/><con:wssContainer/><con:oAuth2ProfileContainer/><con:oAuth1ProfileContainer/></con:soapui-project>